awesome_caller_boi-0.2.4.dist-info/licenses/LICENSE
call_logic/__init__.py
call_logic/core.py
call_logic/models/__init__.py
call_logic/models/transcripts.py
awesome_caller_boi-0.2.4.dist-info/METADATA
awesome_caller_boi-0.2.4.dist-info/WHEEL
awesome_caller_boi-0.2.4.dist-info/top_level.txt
awesome_caller_boi-0.2.4.dist-info/RECORD
