Metadata-Version: 2.4
Name: awesome_caller_boi
Version: 0.2.4
Summary: A FastAPI router + Twilio⇆OpenAI realtime streaming helper
Home-page: https://github.com/torndorff5/awesome_caller_boi
Author: Orndorff Automation
Author-email: torndorff5@gmail.com
Classifier: Programming Language :: Python :: 3
Classifier: Operating System :: OS Independent
Requires-Python: >=3.8
License-File: LICENSE
Requires-Dist: fastapi>=0.70
Requires-Dist: uvicorn>=0.15
Requires-Dist: websockets>=10.0
Requires-Dist: twilio>=7.0
Dynamic: author
Dynamic: author-email
Dynamic: classifier
Dynamic: description
Dynamic: description-content-type
Dynamic: home-page
Dynamic: license-file
Dynamic: requires-dist
Dynamic: requires-python
Dynamic: summary
